docbarcodes/__init__.py
docbarcodes/cli.py
docbarcodes/convertpdf.py
docbarcodes/detect.py
docbarcodes/extract.py
docbarcodes/zxing/__init__.py
docbarcodes/zxing/ex_zxing.py
docbarcodes/zxingjpype/__init__.py
docbarcodes/zxingjpype/extract.py
docbarcodes/zxingjpype/zxingreader.py
docbarcodes/zxingjpype/jars/__init__.py
docbarcodes/zxingjpype/jars/core-3.4.1.jar
docbarcodes/zxingjpype/jars/javase-3.4.1.jar
docbarcodes-1.0.9.dist-info/LICENSE
docbarcodes-1.0.9.dist-info/METADATA
docbarcodes-1.0.9.dist-info/WHEEL
docbarcodes-1.0.9.dist-info/entry_points.txt
docbarcodes-1.0.9.dist-info/top_level.txt
docbarcodes-1.0.9.dist-info/RECORD
