Metadata-Version: 2.1
Name: docbarcodes
Version: 1.0.9
Summary: Docbarcodes extracts 1D and 2D barcodes from scanned PDF documents or images.
Home-page: https://github.com/pypa/docbarcodes
Author: Arlind Nocaj
Author-email: nocaja.r@gmail.com
License: UNKNOWN
Project-URL: Bug Tracker, https://github.com/ArlindNocaj/document-barcodes/issues
Platform: UNKNOWN
Classifier: Programming Language :: Python :: 3
Classifier: Operating System :: OS Independent
Requires-Python: >=3.6
Requires-Dist: pdf2image (==1.16)
Requires-Dist: opencv-python (==4.5.4.60)
Requires-Dist: loguru (==0.5.3)
Requires-Dist: zxingmod (==0.19)
Requires-Dist: pytest (==6.2.5)
Requires-Dist: pytest-regressions (==2.2.0)
Requires-Dist: hypothesis (>=6.31.6)
Requires-Dist: pydantic (==1.8.2)
Requires-Dist: jpype1 (==1.3.0)
Requires-Dist: typer (==0.4.0)
